chunks/__init__.py
chunks/admin.py
chunks/forms.py
chunks/managers.py
chunks/models.py
chunks/urls.py
chunks/views.py
chunks/widgets.py
chunks/locale/ru/LC_MESSAGES/django.mo
chunks/locale/ru/LC_MESSAGES/django.po
chunks/migrations/0001_initial.py
chunks/migrations/0002_group_add.py
chunks/migrations/__init__.py
chunks/static/chunks/chunks.css
chunks/static/chunks/chunks.js
chunks/static/chunks/stub.png
chunks/templates/chunks/editable.html
chunks/templates/chunks/editform.html
chunks/templates/chunks/image.html
chunks/templates/chunks/media.html
chunks/templates/chunks/media_list.html
chunks/templates/chunks/plain.html
chunks/templatetags/__init__.py
chunks/templatetags/chunks.py
django_chunks2-2.8.3.dist-info/DESCRIPTION.rst
django_chunks2-2.8.3.dist-info/METADATA
django_chunks2-2.8.3.dist-info/metadata.json
django_chunks2-2.8.3.dist-info/RECORD
django_chunks2-2.8.3.dist-info/top_level.txt
django_chunks2-2.8.3.dist-info/WHEEL
