Metadata-Version: 2.0
Name: django-chunks2
Version: 2.8.3
Summary: Keyed blocks of content for use in your Django templates
Home-page: https://github.com/gotlium/django-chunks2
Author: gotlium
Author-email: gotlium@gmail.com
License: UNKNOWN
Keywords: django chunks templates
Platform: UNKNOWN
Classifier: Development Status :: 5 - Production/Stable
Classifier: Environment :: Web Environment
Classifier: Framework :: Django
Classifier: Intended Audience :: Developers
Classifier: Operating System :: OS Independent
Classifier: Programming Language :: Python
Classifier: License :: OSI Approved :: BSD License
Classifier: Topic :: Utilities
Requires-Dist: easy-thumbnails
